LICENSE
event_horyzen/__init__.py
event_horyzen/animated_plot.py
event_horyzen/config.yml
event_horyzen/event_horyzen.py
event_horyzen/fantasy.py
event_horyzen-0.1.2.dist-info/entry_points.txt
event_horyzen-0.1.2.dist-info/LICENSE
event_horyzen-0.1.2.dist-info/WHEEL
event_horyzen-0.1.2.dist-info/METADATA
event_horyzen-0.1.2.dist-info/RECORD
