Metadata-Version: 2.1
Name: event-horyzen
Version: 0.1.2
Summary: Simulates geodesic motion around black holes.
Home-page: https://github.com/UCF-SPS-Research-21/event-horyzen
License: GPL-3.0-only
Keywords: black hole,geodesic,simulation
Author: David Wright
Author-email: davecwright@knights.ucf.edu
Requires-Python: >=3.7,<3.11
Classifier: License :: OSI Approved :: GNU General Public License v3 (GPLv3)
Classifier: Programming Language :: Python :: 3
Classifier: Programming Language :: Python :: 3.10
Classifier: Programming Language :: Python :: 3.7
Classifier: Programming Language :: Python :: 3.8
Classifier: Programming Language :: Python :: 3.9
Provides-Extra: pyqt
Requires-Dist: PyOpenGL (>=3.1.5,<4.0.0); extra == "pyqt"
Requires-Dist: PyQt5 (>=5.15.6,<6.0.0); extra == "pyqt"
Requires-Dist: PyYAML (>=6.0,<7.0)
Requires-Dist: h5py (>=3.6.0,<4.0.0)
Requires-Dist: ipython (>=7.30.1,<8.0.0)
Requires-Dist: matplotlib (>=3.5.1,<4.0.0)
Requires-Dist: numpy (>=1.21.5,<2.0.0)
Requires-Dist: pyqtgraph (>=0.12.3,<0.13.0); extra == "pyqt"
Requires-Dist: scipy (>=1.7.3,<2.0.0)
Project-URL: Repository, https://github.com/UCF-SPS-Research-21/event-horyzen
